dtac_tools/__init__.py
dtac_tools/host/__init__.py
dtac_tools/host/default_host.py
dtac_tools/host/plugin_host.py
dtac_tools/host/plugin_pb2.py
dtac_tools/host/plugin_pb2_grpc.py
dtac_tools/host/helpers/__init__.py
dtac_tools/host/helpers/debug_sender.py
dtac_tools/host/helpers/encryptor.py
dtac_tools/host/helpers/network.py
dtac_tools/plugins/__init__.py
dtac_tools/plugins/base.py
dtac_tools/plugins/types.py
dtac_tools/plugins/validation.py
dtac_tools-0.8.26.dist-info/METADATA
dtac_tools-0.8.26.dist-info/WHEEL
dtac_tools-0.8.26.dist-info/top_level.txt
dtac_tools-0.8.26.dist-info/RECORD
